[
  { "id": 1730195374512, "name": "mirza" },
  {
    "id": 1730197095809,
    "name": "mirza",
    "email": "mirza@gmail.com",
    "password": "123"
  },
  {
    "id": 1730202910765,
    "user_id": 1730197095809,
    "task": "i will learn mode js "
  },
  {
    "id": 1730202910765,
    "user_id": 1730197095809,
    "task": "i will learn mode js "
  },
  {
    "id": 1730202910765,
    "taskKey": "something",
    "user_id": 1730197095809,
    "task": "i will learn mode js "
  },
  {
    "id": 1730202910765,
    "user_id": 1730197095809,
    "task": "i will learn mode js"
  },
  {
    "id": 1730202910765,
    "user_id": 1730197095809,
    "task": "i will learn mode js "
  }
]
